{
  "keyword": "曼城",
  "total": 13,
  "results": [
    {
      "title": "今日头条首页",
      "url": "https://www.toutiao.com",
      "platform": "toutiao"
    },
    {
      "title": "Accessibility help",
      "url": "https://support.google.com/websearch/answer/181196?hl=en",
      "platform": "google"
    },
    {
      "title": "懂球帝曼城客战博德闪耀大名单：马尔穆什回归，B席停赛北京时间1月19日，曼城官方公布了欧冠联赛阶段第7轮客场对阵博德闪耀的大名单，其中哈兰德领衔，马尔穆什回归，B席因为累计3张黄牌停赛没有进入名单。.22 hours ago",
      "url": "https://m.dongqiudi.com/article/5618819.html",
      "platform": "google"
    },
    {
      "title": "Sohu全力追击阿森纳！曼城官宣签下格伊 转会费总价3000万镑10 hours ago",
      "url": "https://www.sohu.com/a/977838964_461392?scm=10001.1465_13-100000-0_922.0-0.0-0-0-0-0.a2_5X162X1819",
      "platform": "google"
    },
    {
      "title": "直播吧冬窗第二签！官方：曼城签下25岁水晶宫队长格伊，总价3000万镑17 hours ago",
      "url": "https://news.zhibo8.com/zuqiu/2026-01-19/696e4e1f6d48enative.htm",
      "platform": "google"
    },
    {
      "title": "懂球帝德转列曼城中卫引援花费：格瓦迪奥尔9000万欧居首，格伊第1210 hours ago",
      "url": "https://m.dongqiudi.com/article/5619541.html",
      "platform": "google"
    },
    {
      "title": "星島頭條英超｜马克古希2000万镑加盟曼城 周薪30万镑队中第2高3 hours ago",
      "url": "https://www.stheadline.com/zh-hans/football-news/3537209/%E8%8B%B1%E8%B6%85%E9%A9%AC%E5%85%8B%E5%8F%A4%E5%B8%8C2000%E4%B8%87%E9%95%91%E5%8A%A0%E7%9B%9F%E6%9B%BC%E5%9F%8E-%E5%91%A8%E8%96%AA30%E4%B8%87%E9%95%91%E9%98%9F%E4%B8%AD%E7%AC%AC2%E9%AB%98",
      "platform": "google"
    },
    {
      "title": "View full coverage",
      "url": "https://www.google.com/search?q=%E6%9B%BC%E5%9F%8E&sca_esv=72405467a4d36a9a&tbm=nws&story=GiIIpQEaHQoTc3RvcnlfbGFiZWxfcGFydGlhbBIG5pu85Z-OMjEKJ8yDkoHtlZzf5wHw2ZrZr9GZybwBuerugf3X85TwAZy9xdDvjIntSxC8uKquEBgFcgIQAg&fcs=ABHuY3SsQb-LEXiJUmeZnVcjnyWdLao2Wg&sa=X&ved=2ahUKEwia8Omi35mSAxU5mO4BHXoBNAQQ7IUHegQIFRAF",
      "platform": "google"
    },
    {
      "title": "新唐人電視台英超：曼聯「換帥如換刀」在主場完勝曼城当地时间1月17日，英超联赛第22轮，在“曼市德比”强强对话中，新帅卡里克（Michael Carrick）带领曼联，在主场表现强势，以2:0完胜“同城死敌”曼城，应证了“换帅....13 hours ago",
      "url": "https://www.ntdtv.com/gb/2026/01/19/a104058024.html",
      "platform": "google"
    },
    {
      "title": "ReutersGuardiola shrugs off derby defeat as Man City focus on Champions League progressManchester City have put the weekend defeat by Manchester United behind them, manager Pep Guardiola said on Monday, with the focus on a....14 hours ago",
      "url": "https://www.reuters.com/sports/soccer/guardiola-shrugs-off-derby-defeat-man-city-focus-champions-league-progress-2026-01-19/",
      "platform": "google"
    },
    {
      "title": "星島頭條欧联│打吡创伤后遇初哥 曼城必打争气「波」曼城质素之高毋庸置疑，却刚在曼市打吡受创，更急须一场胜仗反弹，眼前遇弱旅定不留手。曼城有表现愈见成熟的翼锋谢利美杜古于边路发难，今晚即使远征北欧....10 hours ago",
      "url": "https://www.stheadline.com/zh-hans/football-betting/3536982/%E6%AC%A7%E8%81%94%E6%89%93%E5%90%A1%E5%88%9B%E4%BC%A4%E5%90%8E%E9%81%87%E5%88%9D%E5%93%A5-%E6%9B%BC%E5%9F%8E%E5%BF%85%E6%89%93%E4%BA%89%E6%B0%94%E6%B3%A2",
      "platform": "google"
    },
    {
      "title": "Trending now",
      "url": "https://www.bing.com/news/search?q=Top+stories&nvaug=%5bNewsVertical+Category%3d%22rt_MaxClass%22%5d&FORM=NSBABR",
      "platform": "bing"
    },
    {
      "title": "Trending now",
      "url": "https://www.bing.com/news/search?q=%e6%9b%bc%e5%9f%8e&qft=sortbydate%3d%221%22&form=YFNR",
      "platform": "bing"
    }
  ],
  "platforms": [
    "toutiao",
    "google",
    "bing"
  ],
  "timestamp": "2026-01-20T08:54:27.866391",
  "run_id": "21165215910",
  "run_number": "15",
  "filename": "results_21165215910_15_20260120_085427.json"
}